sapl_flask/__init__.py
sapl_flask/flask_authorization_subscription_factory.py
SAPL_Flask-0.3.5.dist-info/LICENSE
SAPL_Flask-0.3.5.dist-info/METADATA
SAPL_Flask-0.3.5.dist-info/WHEEL
SAPL_Flask-0.3.5.dist-info/top_level.txt
SAPL_Flask-0.3.5.dist-info/RECORD
