Metadata-Version: 2.1
Name: SAPL-Flask
Version: 0.3.5
Summary: Library to integrate SAPL into a Flask project
Author-email: Dominic Heutelbeck <dominic@heutelbeck.com>
License: Copyright 2017-2022 Dominic Heutelbeck
Project-URL: Homepage, https://sapl.io/
Project-URL: Documentation, https://sapl.io/documentation
Project-URL: Source, https://github.com/heutelbeck/sapl-python/tree/master/sapl_base
Keywords: SAPL,ABAC,Security,Access control
Classifier: Framework :: Flask
Classifier: Programming Language :: Python :: 3
License-File: LICENSE
Requires-Dist: flask
Requires-Dist: sapl-base
